rendergraphapi/__init__.py
rendergraphapi/render_graph_api.py
rendergraphapi/schema.py
rendergraphapi-0.0.3.dist-info/METADATA
rendergraphapi-0.0.3.dist-info/WHEEL
rendergraphapi-0.0.3.dist-info/top_level.txt
rendergraphapi-0.0.3.dist-info/RECORD
