Metadata-Version: 2.1
Name: rendergraphapi
Version: 0.0.3
Summary: Render.com Graph API
Home-page: https://github.com/idealoop/rendergraphapi
Author: idealoop
Author-email: noreply@idea-loop.com
License: MIT
Requires-Dist: pydantic
Requires-Dist: requests
Requires-Dist: authenticator
